README
dist.sh
doapfiend-gentoo.rdf
doapfiend_gentoo.py
setup.py
doapfiend_gentoo.egg-info/PKG-INFO
doapfiend_gentoo.egg-info/SOURCES.txt
doapfiend_gentoo.egg-info/dependency_links.txt
doapfiend_gentoo.egg-info/entry_points.txt
doapfiend_gentoo.egg-info/top_level.txt